{
  "_id": "WCe3fDT7eNXtdvWD",
  "_key": "!actors!WCe3fDT7eNXtdvWD",
  "name": "Ant, Giant, Worker",
  "type": "npc",
  "img": "icons/creatures/invertebrates/ant-strength-green.webp",
  "system": {
    "attributes": {
      "str": {
        "value": 10
      },
      "dex": {
        "value": 7
      },
      "end": {
        "value": 12
      },
      "int": {
        "value": 0
      },
      "edu": {
        "value": 7
      },
      "soc": {
        "value": 12
      }
    },
    "lifeblood": {
      "value": 26,
      "max": 26
    },
    "stamina": {
      "value": 13,
      "max": 13
    },
    "spellcaster": false,
    "monster": true,
    "notes": "100kg Beast (Eater), plains walker, #App: 4d6, Treasure: Incidental. Mandibles (2d6); armor 3; speed 10m/action; Morale -2. An enormous and hardy insect, the giant ant lives in massive nests and eat almost anything, hapless adventurers included. Note that the behavior notes above are for a wilderness encounter; giant ants will defend their nest to the death if invaded.",
    "skills": {
      "alchemy": -3,
      "animals": -3,
      "artifice": -3,
      "artillery": -3,
      "art": -3,
      "athletics": 1,
      "archery": -3,
      "battle": -3,
      "carousing": -3,
      "craft": -3,
      "deception": -3,
      "govern": -3,
      "insight": -3,
      "jackoftrades": -3,
      "leadership": -3,
      "liaison": -3,
      "healing": -3,
      "meleecombat": 0,
      "naturalphilosophy": -3,
      "scout": -3,
      "sorcery": -3,
      "sneak": -3,
      "steward": -3,
      "streetwise": -3,
      "survival": -3,
      "religion": -3,
      "riding": -3,
      "watercraft": -3
    }
  },
  "items": [
    {
      "_id": "FDTA7Xrc5UTIdDkd",
      "_key": "!actors.items!WCe3fDT7eNXtdvWD.FDTA7Xrc5UTIdDkd",
      "name": "Natural Armor",
      "type": "armor",
      "img": "icons/equipment/chest/vest-bulletproof-body-armor.webp",
      "system": {
        "description": "",
        "cost": "",
        "shield": false,
        "protection": 3,
        "sneakModifier": 0,
        "encumbrance": 0,
        "equipped": true
      },
      "effects": [],
      "folder": null,
      "sort": 0,
      "ownership": {
        "default": 0
      },
      "flags": {},
      "_stats": {}
    },
    {
      "_id": "9YMrfF0rir1agkKj",
      "_key": "!actors.items!WCe3fDT7eNXtdvWD.9YMrfF0rir1agkKj",
      "name": "Mandibles",
      "type": "weapon",
      "img": "icons/weapons/swords/sword-broad-worn.webp",
      "system": {
        "description": "",
        "cost": "",
        "damage": "2d6",
        "range": "",
        "aspects": "Natural Weapon",
        "ammo": 0,
        "ammoMax": 0,
        "ammoCost": "",
        "ammoType": "",
        "thrown": false,
        "ranged": false,
        "artillery": false,
        "encumbrance": 0,
        "equipped": true
      },
      "effects": [],
      "folder": null,
      "sort": 0,
      "ownership": {
        "default": 0
      },
      "flags": {},
      "_stats": {}
    }
  ],
  "effects": [],
  "folder": null,
  "sort": 0,
  "ownership": {
    "default": 0
  },
  "flags": {},
  "_stats": {},
  "prototypeToken": {
    "bar1": {
      "attribute": "lifeblood"
    },
    "bar2": {
      "attribute": "stamina"
    }
  }
}